fluprodia/__init__.py
fluprodia/_utils.py
fluprodia/fluid_property_diagram.py
fluprodia-4.0.dist-info/licenses/LICENSE
fluprodia-4.0.dist-info/WHEEL
fluprodia-4.0.dist-info/METADATA
fluprodia-4.0.dist-info/RECORD
