Metadata-Version: 2.4
Name: fluprodia
Version: 4.0
Summary: Create beautiful fluid property diagrams using CoolProp and matplotlib
Author-email: Francesco Witte <tespy@witte.sh>
Requires-Python: >=3.9
Classifier: Development Status :: 5 - Production/Stable
Classifier: Intended Audience :: Education
Classifier: Intended Audience :: Science/Research
Classifier: License :: OSI Approved :: MIT License
Classifier: Operating System :: Microsoft :: Windows
Classifier: Operating System :: POSIX
Classifier: Operating System :: Unix
Classifier: Programming Language :: Python
Classifier: Programming Language :: Python :: 3.9
Classifier: Programming Language :: Python :: 3.10
Classifier: Programming Language :: Python :: 3.11
Classifier: Topic :: Scientific/Engineering
License-File: LICENSE
Requires-Dist: CoolProp>=6.4
Requires-Dist: numpy>=1.13.3
Requires-Dist: build ; extra == "dev"
Requires-Dist: flit ; extra == "dev"
Requires-Dist: furo ; extra == "dev"
Requires-Dist: matplotlib ; extra == "dev"
Requires-Dist: pytest ; extra == "dev"
Requires-Dist: sphinx>=7.2.2 ; extra == "dev"
Requires-Dist: sphinx-copybutton ; extra == "dev"
Requires-Dist: sphinx-design ; extra == "dev"
Requires-Dist: tespy ; extra == "dev"
Requires-Dist: tox ; extra == "dev"
Project-URL: Changelog, https://fluprodia.readthedocs.io/en/latest/changelog.html
Project-URL: Documentation, https://fluprodia.readthedocs.io/
Project-URL: Homepage, https://github.com/fwitte/fluprodia
Project-URL: Issue Tracker, https://github.com/fwitte/fluprodia/issues
Provides-Extra: dev
